odoo/addons/partner_restrict_payment_acquirer/README.rst
odoo/addons/partner_restrict_payment_acquirer/__init__.py
odoo/addons/partner_restrict_payment_acquirer/__manifest__.py
odoo/addons/partner_restrict_payment_acquirer/i18n/partner_restrict_payment_acquirer.pot
odoo/addons/partner_restrict_payment_acquirer/models/__init__.py
odoo/addons/partner_restrict_payment_acquirer/models/payment_acquirer.py
odoo/addons/partner_restrict_payment_acquirer/models/res_partner.py
odoo/addons/partner_restrict_payment_acquirer/readme/DESCRIPTION.rst
odoo/addons/partner_restrict_payment_acquirer/readme/ROADMAP.rst
odoo/addons/partner_restrict_payment_acquirer/readme/USAGE.rst
odoo/addons/partner_restrict_payment_acquirer/static/description/icon.png
odoo/addons/partner_restrict_payment_acquirer/static/description/index.html
odoo/addons/partner_restrict_payment_acquirer/tests/__init__.py
odoo/addons/partner_restrict_payment_acquirer/tests/test_payment_acquirer.py
odoo/addons/partner_restrict_payment_acquirer/views/payment_templates.xml
odoo/addons/partner_restrict_payment_acquirer/views/res_partner_views.xml
odoo13_addon_partner_restrict_payment_acquirer-13.0.1.0.1.dev3.dist-info/METADATA
odoo13_addon_partner_restrict_payment_acquirer-13.0.1.0.1.dev3.dist-info/WHEEL
odoo13_addon_partner_restrict_payment_acquirer-13.0.1.0.1.dev3.dist-info/top_level.txt
odoo13_addon_partner_restrict_payment_acquirer-13.0.1.0.1.dev3.dist-info/RECORD
